eddie_cli/.mirascope/prompt_template.j2
eddie_cli/.mirascope/versions/eddie_chat/0001_eddie_chat.py
eddie_cli/.mirascope/versions/eddie_chat/0002_eddie_chat.py
eddie_cli/.mirascope/versions/eddie_chat/0003_eddie_chat.py
eddie_cli/.mirascope/versions/eddie_chat/0004_eddie_chat.py
eddie_cli/.mirascope/versions/eddie_chat/0005_eddie_chat.py
eddie_cli/.mirascope/versions/eddie_chat/0006_eddie_chat.py
eddie_cli/.mirascope/versions/eddie_chat/version.txt
eddie_cli/__init__.py
eddie_cli/app.py
eddie_cli/app.tcss
eddie_cli/calls/__init__.py
eddie_cli/calls/eddie_chat.py
eddie_cli/main.py
eddie_cli/mirascope.ini
eddie_cli-0.1.0.dist-info/LICENSE
eddie_cli-0.1.0.dist-info/METADATA
eddie_cli-0.1.0.dist-info/WHEEL
eddie_cli-0.1.0.dist-info/entry_points.txt
eddie_cli-0.1.0.dist-info/RECORD
