Metadata-Version: 2.1
Name: eddie-cli
Version: 0.1.0
Summary: Eddie -- the retro AI-powered CLI assistant
License: MIT
Author: William Bakst
Author-email: william@mirascope.io
Requires-Python: >=3.9,<4.0
Classifier: License :: OSI Approved :: MIT License
Classifier: Programming Language :: Python :: 3
Classifier: Programming Language :: Python :: 3.9
Classifier: Programming Language :: Python :: 3.10
Classifier: Programming Language :: Python :: 3.11
Classifier: Programming Language :: Python :: 3.12
Requires-Dist: asyncer (>=0.0.7,<0.0.8)
Requires-Dist: mirascope[cli] (>=0.14.1,<0.15.0)
Requires-Dist: textual (>=0.63.2,<0.64.0)
Requires-Dist: typer (>=0.12.3,<0.13.0)
